orthosnap/__init__.py
orthosnap/__main__.py
orthosnap/args_processing.py
orthosnap/helper.py
orthosnap/orthosnap.py
orthosnap/parser.py
orthosnap/version.py
orthosnap/writer.py
orthosnap-1.4.0.dist-info/LICENSE.md
orthosnap-1.4.0.dist-info/METADATA
orthosnap-1.4.0.dist-info/WHEEL
orthosnap-1.4.0.dist-info/entry_points.txt
orthosnap-1.4.0.dist-info/top_level.txt
orthosnap-1.4.0.dist-info/RECORD
