Metadata-Version: 2.1
Name: orthosnap
Version: 1.4.0
Summary: orthosnap, identify orthologous subgroups of genes in large orthologous groups of genes.
Home-page: https://github.com/jlsteenwyk/orthosnap
Author: Jacob L. Steenwyk
Author-email: jlsteenwyk@gmail.com
Classifier: Operating System :: OS Independent
Classifier: Intended Audience :: Science/Research
Classifier: Programming Language :: Python
Classifier: Programming Language :: Python :: 3.9
Classifier: Programming Language :: Python :: 3.10
Classifier: Programming Language :: Python :: 3.11
Classifier: Programming Language :: Python :: 3.12
Classifier: Programming Language :: Python :: 3.13
Classifier: Topic :: Scientific/Engineering
Requires-Python: >=3.9
License-File: LICENSE.md
Requires-Dist: biopython >=1.85
Requires-Dist: numpy >=2.1
Requires-Dist: tqdm >=4.66.1
